biblio2023/__init__.py
biblio2023/biblio.pyd
biblio2023-1.0.0.dist-info/LICENSE
biblio2023-1.0.0.dist-info/WHEEL
biblio2023-1.0.0.dist-info/METADATA
biblio2023-1.0.0.dist-info/RECORD
