Metadata-Version: 2.1
Name: biblio2023
Version: 1.0.0
Summary: Test Documentation
Author-email: Mamiyou <karamArtz@gmail.com>
Classifier: License :: OSI Approved :: MIT License
